gefragt_gejagt/__init__.py
gefragt_gejagt/__main__.py
gefragt_gejagt/game.py
gefragt_gejagt/offer.py
gefragt_gejagt/player.py
gefragt_gejagt/question.py
gefragt_gejagt/round.py
gefragt_gejagt/team.py
gefragt_gejagt-0.0.2.dist-info/LICENSE
gefragt_gejagt-0.0.2.dist-info/METADATA
gefragt_gejagt-0.0.2.dist-info/WHEEL
gefragt_gejagt-0.0.2.dist-info/top_level.txt
gefragt_gejagt-0.0.2.dist-info/RECORD
