Metadata-Version: 2.1
Name: gefragt-gejagt
Version: 0.0.2
Summary: The studio software for the quizgame 'Gefragt Gejagt'
Home-page: https://github.com/nkreer/gefragt-gejagt-studio
Author: Simeon Keske, Der mit dem Zopf
Author-email: simeon@noemis.me, der@mit-dem-zopf.cf
License: UNKNOWN
Platform: UNKNOWN
Classifier: Development Status :: 4 - Beta
Classifier: Programming Language :: Python :: 3
Classifier: License :: OSI Approved :: European Union Public Licence 1.2 (EUPL 1.2)
Classifier: Operating System :: OS Independent
Classifier: Natural Language :: German
Classifier: Topic :: Games/Entertainment
Requires-Python: >=3.6
Requires-Dist: eel
